darksoulsapi/__init__.py
darksoulsapi/feature_matching.py
darksoulsapi/fitness_function.py
darksoulsapi/game_save.py
darksoulsapi/gamestate.py
darksoulsapi/key_output.py
darksoulsapi/requirements.txt
darksoulsapi/start_game.py
darksoulsapi/windowcapture.py
darksoulsapi/Dark Souls Save Files/Asylum Demon/DRAKS0005.sl2
darksoulsapi/Dark Souls Save Files/Asylum Demon Defeated/DRAKS0005.sl2
darksoulsapi/Dark Souls Save Files/Beginning/DRAKS0005.sl2
darksoulsapi/Dark Souls Save Files/Bell Gargoyles/DRAKS0005.sl2
darksoulsapi/Dark Souls Save Files/Capra Demon/DRAKS0005.sl2
darksoulsapi/Dark Souls Save Files/Chaos Witch Quelaag/DRAKS0005.sl2
darksoulsapi/Dark Souls Save Files/Gaping Dragon/DRAKS0005.sl2
darksoulsapi/Dark Souls Save Files/Great Grey Wolf Sif/DRAKS0005.sl2
darksoulsapi/Dark Souls Save Files/Iron Golem/DRAKS0005.sl2
darksoulsapi/Dark Souls Save Files/Moonlight Butterfly/DRAKS0005.sl2
darksoulsapi/Dark Souls Save Files/Taurus Demon/DRAKS0005.sl2
darksoulsapi/examples/config-feedforward.cfg
darksoulsapi/examples/ds_environment_NEAT.py
darksoulsapi/examples/ds_environment_random.py
darksoulsapi/templates/health_bar.png
darksoulsapi/templates/is_dead.png
darksoulsapi/templates/is_revived.png
darksoulsapi/templates/loading_into_game.png
darksoulsapi/templates/main_menu.png
darksoulsapi/templates/status_bar.png
darksoulsapi/templates/target_template1.png
darksoulsapi/templates/target_template2.png
darksoulsapi/templates/traverse_the_white_light.png
darksoulsapi/templates/victory_achieved.png
darksoulsapi/test_functions/show_visual_feed.py
darksoulsapi/config.toml
darksoulsapi/templates/health_bar.png
darksoulsapi/templates/is_dead.png
darksoulsapi/templates/is_revived.png
darksoulsapi/templates/loading_into_game.png
darksoulsapi/templates/main_menu.png
darksoulsapi/templates/status_bar.png
darksoulsapi/templates/target_template1.png
darksoulsapi/templates/target_template2.png
darksoulsapi/templates/traverse_the_white_light.png
darksoulsapi-0.0.1.dist-info/METADATA
darksoulsapi-0.0.1.dist-info/WHEEL
darksoulsapi-0.0.1.dist-info/licenses/LICENSE
darksoulsapi-0.0.1.dist-info/RECORD
