Metadata-Version: 2.4
Name: darksoulsapi
Version: 0.0.1
Summary: A Dark Souls: Remastered API for AI research
Project-URL: Homepage, https://github.com/joconno2/dsapi
Project-URL: Issues, https://github.com/joconno2/dsapi/issues
Author-email: Mustafa Bugti <mbugti@conncoll.edu>
License-Expression: MIT
License-File: LICENSE
Classifier: Operating System :: Microsoft :: Windows
Classifier: Programming Language :: Python :: 3
Requires-Python: >=3.12
Requires-Dist: keyboard>=0.13.5
Requires-Dist: numpy>=2.1.3
Requires-Dist: opencv-python>=4.10.0.84
Requires-Dist: pytesseract>=0.3.13
Requires-Dist: pywin32; sys_platform == 'win32'
